decapitaliza/__init__.py
decapitaliza/decapitaliza.py
decapitaliza/resources/dictionary.bin
decapitaliza-0.1.2.dist-info/METADATA
decapitaliza-0.1.2.dist-info/WHEEL
decapitaliza-0.1.2.dist-info/entry_points.txt
decapitaliza-0.1.2.dist-info/licenses/LICENSE
decapitaliza-0.1.2.dist-info/RECORD
