Metadata-Version: 2.1
Name: decapitaliza
Version: 0.1.2
Summary: A simple CLI tool to decapitalize spanish strings.
Author-email: juan.pablo.de.castro@gmail.com
License-Expression: MIT
License-File: LICENSE
Classifier: Development Status :: 4 - Beta
Classifier: Environment :: Console
Classifier: Intended Audience :: System Administrators
Classifier: License :: OSI Approved :: MIT License
Classifier: Operating System :: OS Independent
Classifier: Programming Language :: Python :: 3.9
Classifier: Programming Language :: Python :: 3.10
Classifier: Topic :: Text Processing :: Linguistic
Classifier: Topic :: Utilities
Requires-Dist: click>=7.0
Requires-Dist: unidecode>=1.1.1
